[{"s": "marshrutizator-rostelekom-chto-eto-takoe", "t": "Маршрутизатор Ростелеком: что это, как работает и как настроить", "i": "🖥️", "c": "oborudovanie"}, {"s": "marshrutizator-rostelekom-eto-chto", "t": "Маршрутизатор Ростелеком: что это, как работает и какой выбрать", "i": "🖥️", "c": "oborudovanie"}, {"s": "match-hd-kakoj-nomer-kanala-rostelekom", "t": "Матч ТВ HD: какой номер канала у Ростелеком", "i": "📺", "c": "podklyuchenie-tv"}, {"s": "marina-roshcha-rostelekom-kak-dojti-ot-metro", "t": "Марьина Роща Ростелеком: как дойти от метро и где офис", "i": "📍", "c": "kontakty-i-ofisy"}, {"s": "marusya-rostelekom-chto-eto", "t": "Маруся Ростелеком: что это и как настроить голосового ассистента", "i": "🏠", "c": "umnyj-dom"}, {"s": "maska-routera-rostelekom-kak-uznat", "t": "Как узнать маску роутера Ростелеком: адреса и настройки", "i": "🖥️", "c": "oborudovanie"}, {"s": "match-hd-rostelekom-tv-kakoj-kanal", "t": "Матч HD Ростелеком ТВ: на каком канале смотреть", "i": "📺", "c": "podklyuchenie-tv"}, {"s": "match-boets-rostelekom-kakoj-kanal", "t": "Матч боец Ростелеком: какой канал смотреть, как найти", "i": "📺", "c": "podklyuchenie-tv"}, {"s": "match-premer-kakaya-knopka-rostelekom", "t": "Матч Премьер Ростелеком: как подключить и где кнопка", "i": "📺", "c": "podklyuchenie-tv"}, {"s": "match-premer-kakoj-nomer-kanala-na-rostelekom", "t": "Матч Премьер на Ростелеком: номер канала и как смотреть", "i": "📺", "c": "podklyuchenie-tv"}, {"s": "marshrutizator-kak-nastroit-rostelekom", "t": "Как настроить маршрутизатор Ростелеком: пошаговая инструкция", "i": "🖥️", "c": "oborudovanie"}, {"s": "maska-rostelekom-chto-eto", "t": "Маска Ростелеком: настройки, значение и как изменить", "i": "📶", "c": "nastrojka-wi-fi"}, {"s": "match-tv-rostelekom-kakoj-kanal", "t": "Матч ТВ на Ростелеком: номер канала и как найти", "i": "📺", "c": "podklyuchenie-tv"}, {"s": "marina-roshcha-sushchevskij-val-26-rostelekom-kak-doekhat", "t": "Как доехать до офиса Ростелеком на Сущевском Валу 26", "i": "📍", "c": "kontakty-i-ofisy"}, {"s": "match-tv-kakoj-nomer-kanala-na-rostelekom", "t": "Матч ТВ на Ростелеком: номер канала и как смотреть", "i": "📺", "c": "podklyuchenie-tv"}, {"s": "makroregionalnyj-filial-yug-oao-rostelekom-chto-eto", "t": "МРФ Юг Ростелеком: структура, зоны покрытия и контакты", "i": "📍", "c": "kontakty-i-ofisy"}, {"s": "match-igra-kakoj-kanal-na-rostelekom", "t": "Какой канал покажет матч на Ростелеком: гид по сервису Wink", "i": "🎬", "c": "servis-wink"}, {"s": "match-boets-kakoj-nomer-kanala-rostelekom", "t": "Матч! Боец: номер канала Ростелеком и как подключить", "i": "📺", "c": "podklyuchenie-tv"}, {"s": "match-strana-kakoj-kanal-na-rostelekom", "t": "Матч Страна на Ростелеком: канал, тарифы и настройка", "i": "📺", "c": "podklyuchenie-tv"}, {"s": "match-tv-hd-kakoj-kanal-rostelekom-na-televizore", "t": "Матч ТВ HD на Ростелеком: номер канала и настройка", "i": "📺", "c": "podklyuchenie-tv"}, {"s": "match-strana-kakoj-nomer-kanala-rostelekom", "t": "Номер канала Матч Страна Ростелеком: где найти и как смотреть", "i": "📺", "c": "podklyuchenie-tv"}, {"s": "marshrutizator-fttx-rostelekom-chto-eto", "t": "Маршрутизатор FTTx Ростелеком: что это и как настроить", "i": "🖥️", "c": "oborudovanie"}, {"s": "master-nastrojki-oborudovaniya-rostelekom-kak-nastroit", "t": "Мастер настройки оборудования Ростелеком: пошаговая инструкция", "i": "🖥️", "c": "oborudovanie"}, {"s": "match-strana-kakoj-kanal-po-televizoru-rostelekom", "t": "Матч Страна на Ростелеком: как найти и смотреть на TV", "i": "📺", "c": "podklyuchenie-tv"}, {"s": "marshrutizator-wifi-rostelekom-kak-nastroit", "t": "Настройка маршрутизатора Wi-Fi Ростелеком: инструкция", "i": "📶", "c": "nastrojka-wi-fi"}, {"s": "mag-250-pristavka-rostelekom-kak-smotret-besplatno-vse-kanaly-iptv", "t": "Настройка IPTV на MAG 250 от Ростелеком бесплатно", "i": "🖥️", "c": "oborudovanie"}, {"s": "malenkaya-skorost-interneta-rostelekom-kak-ispravit", "t": "Маленькая скорость интернета Ростелеком: как исправить самому", "i": "🛠️", "c": "reshenie-problem"}, {"s": "maska-shlyuz-gde-posmotret-rostelekom", "t": "Как найти маску и шлюз Ростелеком: где посмотреть в настройках", "i": "📶", "c": "nastrojka-wi-fi"}, {"s": "match-futbol-1-kakoj-nomer-kanala-na-rostelekom", "t": "Матч футбола на «Ростелеком»: номер канала и пакет", "i": "📺", "c": "podklyuchenie-tv"}, {"s": "match-tv-hd-rostelekom-kakoj-nomer", "t": "Матч ТВ HD на Ростелеком: номер канала и способы подключения", "i": "📺", "c": "podklyuchenie-tv"}, {"s": "marusya-ot-rostelekom-chto-eto-takoe-i-kak", "t": "Маруся от Ростелеком: настройка, функции и управление", "i": "🏠", "c": "umnyj-dom"}, {"s": "matrix-p2p-rostelekom-chto-eto-takoe", "t": "Matrix P2P Ростелеком: что это и как работает | Подробный разбор", "i": "🖥️", "c": "oborudovanie"}, {"s": "maska-podseti-kak-uznat-rostelekom", "t": "Маска подсети Ростелеком: как узнать и настроить", "i": "📶", "c": "nastrojka-wi-fi"}, {"s": "match-premer-kakoj-kanal-nomer-rostelekom", "t": "Матч Премьер Ростелеком: номер канала и как подключить", "i": "📺", "c": "podklyuchenie-tv"}, {"s": "match-arena-kakoj-kanal-rostelekom", "t": "Матч Арена: какой канал Ростелеком и где смотреть", "i": "🎬", "c": "servis-wink"}, {"s": "match-tv-hd-rostelekom-kakoj", "t": "Матч ТВ HD Ростелеком: какой номер канала и тариф", "i": "📺", "c": "podklyuchenie-tv"}, {"s": "mac-filtr-rostelekom-chto-eto", "t": "MAC-фильтр Ростелеком: что это и как настроить", "i": "📶", "c": "nastrojka-wi-fi"}]